portablemc_forge/__init__.py
portablemc_forge/wrapper/.gitignore
portablemc_forge/wrapper/pom.xml
portablemc_forge/wrapper/src/main/java/argo/jdom/AbstractJsonObject.java
portablemc_forge/wrapper/src/main/java/argo/jdom/JsonConstants.java
portablemc_forge/wrapper/src/main/java/argo/jdom/JsonField.java
portablemc_forge/wrapper/src/main/java/argo/jdom/JsonNode.java
portablemc_forge/wrapper/src/main/java/argo/jdom/JsonNodeFactories.java
portablemc_forge/wrapper/src/main/java/argo/jdom/JsonNodeType.java
portablemc_forge/wrapper/src/main/java/argo/jdom/JsonObject.java
portablemc_forge/wrapper/src/main/java/argo/jdom/JsonRootNode.java
portablemc_forge/wrapper/src/main/java/argo/jdom/JsonStringNode.java
portablemc_forge/wrapper/src/main/java/com/google/common/base/Predicate.java
portablemc_forge/wrapper/src/main/java/net/minecraftforge/installer/actions/Action.java
portablemc_forge/wrapper/src/main/java/net/minecraftforge/installer/actions/ActionCanceledException.java
portablemc_forge/wrapper/src/main/java/net/minecraftforge/installer/actions/ClientInstall.java
portablemc_forge/wrapper/src/main/java/net/minecraftforge/installer/actions/ProgressCallback.java
portablemc_forge/wrapper/src/main/java/net/minecraftforge/installer/ActionType.java
portablemc_forge/wrapper/src/main/java/net/minecraftforge/installer/ClientInstall.java
portablemc_forge/wrapper/src/main/java/net/minecraftforge/installer/json/Install.java
portablemc_forge/wrapper/src/main/java/net/minecraftforge/installer/json/InstallV1.java
portablemc_forge/wrapper/src/main/java/net/minecraftforge/installer/json/Util.java
portablemc_forge/wrapper/src/main/java/net/minecraftforge/installer/package-info.java
portablemc_forge/wrapper/src/main/java/net/minecraftforge/installer/ServerInstall.java
portablemc_forge/wrapper/src/main/java/net/minecraftforge/installer/SimpleInstaller.java
portablemc_forge/wrapper/src/main/java/net/minecraftforge/installer/VersionInfo.java
portablemc_forge-2.0.2.dist-info/WHEEL
portablemc_forge-2.0.2.dist-info/METADATA
portablemc_forge-2.0.2.dist-info/RECORD
